embed_clustering/__init__.py
embed_clustering/latent_component.py
embed_clustering/__pycache__/latent_component.cpython-38.pyc
embed_clustering-0.0.5.dist-info/METADATA
embed_clustering-0.0.5.dist-info/WHEEL
embed_clustering-0.0.5.dist-info/top_level.txt
embed_clustering-0.0.5.dist-info/RECORD
