Metadata-Version: 2.1
Name: embed-clustering
Version: 0.0.5
Summary: Clustering using different non-parameteric models with the combination of word Embedding
Home-page: https://github.com/dreji18/embed-clustering
Author: Masume Azizyan, Deepak John Reji
Author-email: masume.azee@gmail.com
License: MIT
Classifier: License :: OSI Approved :: MIT License
Classifier: Programming Language :: Python :: 3.6
Classifier: Programming Language :: Python :: 3.7
Classifier: Programming Language :: Python :: 3.8
Classifier: Programming Language :: Python :: 3.9
Requires-Dist: pandas
Requires-Dist: tweet-preprocessor
Requires-Dist: numpy
Requires-Dist: sentence-transformers
